cat_tools/__init__.py
cat_tools/cat.py
cat_tools-1.4.0.dist-info/LICENSE
cat_tools-1.4.0.dist-info/METADATA
cat_tools-1.4.0.dist-info/WHEEL
cat_tools-1.4.0.dist-info/top_level.txt
cat_tools-1.4.0.dist-info/RECORD
